henau_auth/__init__.py
henau_auth/agent/__init__.py
henau_auth/agent/llm.py
henau_auth/casbin/__init__.py
henau_auth/casbin/model.conf
henau_auth/casbin/rbac.py
henau_auth/core.py
henau_auth/fastapi/__init__.py
henau_auth/fastapi/admin_server/admin_server.py
henau_auth/fastapi/admin_server/admin_server_app.py
henau_auth/fastapi/login.py
henau_auth/fastapi/oauth_henau.py
henau_auth/fastapi/templates/login.html
henau_auth/fastapi/utils/jwt.py
henau_auth/message/__init__.py
henau_auth/message/base_message.py
henau_auth/message/super_message.py
henau_auth/oauth2/__init__.py
henau_auth/oauth2/super_auth.py
henau_auth-0.1.9.dist-info/LICENSE
henau_auth-0.1.9.dist-info/METADATA
henau_auth-0.1.9.dist-info/WHEEL
henau_auth-0.1.9.dist-info/entry_points.txt
henau_auth-0.1.9.dist-info/RECORD
