Metadata-Version: 2.3
Name: henau-auth
Version: 0.1.9
Summary: 河南农业大学统一授权认证服务 python SDK
Author: Tordor
Author-email: 3262978839@qq.com
Requires-Python: >=3.10
Classifier: Programming Language :: Python :: 3
Classifier: Programming Language :: Python :: 3.10
Classifier: Programming Language :: Python :: 3.11
Classifier: Programming Language :: Python :: 3.12
Classifier: Programming Language :: Python :: 3.13
Requires-Dist: casbin (>=1.43.0)
Requires-Dist: casbin-peewee-adapter (>=0.0.2)
Requires-Dist: jinja2 (>=3.1.6)
Requires-Dist: mcp (>=1.9.0)
Requires-Dist: ollama (>=0.4.8)
Requires-Dist: peewee (>=3.18.1)
Requires-Dist: pyjwt (>=2.10.1)
Requires-Dist: requests (>=2.32.3)
Requires-Dist: starlette (>=0.46.2)
Requires-Dist: typer (>=0.15.3)
